<problem url_name="problem_709d0a916153be1d6e629c5919f02e81">
  <choiceresponse>
    <label>For this patient, the local SHAP explanation shows that:<ul><li><code>thal_3</code> and <code>oldpeak</code> push the prediction toward <strong>lower</strong> risk</li><li><code>ca_0</code> and <code>chol</code> push the prediction toward <strong>higher</strong> risk</li></ul> Which statements are justified based on this information? (Select all that apply.)</label>
    <checkboxgroup>
      <choice correct="true">The model identified both risk-increasing and risk-decreasing factors for this patient.</choice>
      <choice correct="false">The presence of <code>thal_3</code> and <code>oldpeak</code> means the patient should be classified as low risk.</choice>
      <choice correct="true">The prediction reflects a tradeoff between different clinical factors for this patient.</choice>
      <choice correct="false">The model considers only the features that push risk upward when making a prediction.</choice>
      <choice correct="true">This pattern of effects may differ for another patient with different characteristics.</choice>
    </checkboxgroup>
  </choiceresponse>
  <solution>
    <div class="detailed-solution">
      <p>Explanation</p>
      <p>A local SHAP explanation highlights how different features influenced the model’s prediction for a specific patient. The SHAP values show that some features push this patient’s predicted risk upward (<code>ca_0 </code>and <code>chol</code>), while others push it downward (<code>thal_3</code> and <code>oldpeak</code>). This indicates that the model is weighing multiple, potentially conflicting pieces of information for the same patient. Importantly, this reasoning is patient-specific: a different patient may show a different pattern of influential features depending on their characteristics.</p>
    </div>
  </solution>
</problem>
